{
	"apn_interface_version": "2",
	"APN_config0": "AT($)($)manual($)*99#($)none($)($)($)IP($)auto($)($)auto($)($)",
	"APN_config1": "ProfileSami($)internet($)manual($)*99#($)none($)($)($)IP($)auto($)($)auto($)($)",
	"APN_config2": "",
	"APN_config3": "",
	"APN_config4": "",
	"APN_config5": "",
	"APN_config6": "",
	"APN_config7": "",
	"APN_config8": "",
	"APN_config9": "",
	"APN_config10": "",
	"APN_config11": "",
	"APN_config12": "",
	"APN_config13": "",
	"APN_config14": "",
	"APN_config15": "",
	"APN_config16": "",
	"APN_config17": "",
	"APN_config18": "",
	"APN_config19": "",
	"ipv6_APN_config0": "AT($)($)($)($)($)($)($)($)($)($)($)($)",
	"ipv6_APN_config1": "ProfileSami($)($)($)($)($)($)($)($)($)($)($)($)",
	"ipv6_APN_config2": "",
	"ipv6_APN_config3": "",
	"ipv6_APN_config4": "",
	"ipv6_APN_config5": "",
	"ipv6_APN_config6": "",
	"ipv6_APN_config7": "",
	"ipv6_APN_config8": "",
	"ipv6_APN_config9": "",
	"ipv6_APN_config10": "",
	"ipv6_APN_config11": "",
	"ipv6_APN_config12": "",
	"ipv6_APN_config13": "",
	"ipv6_APN_config14": "",
	"ipv6_APN_config15": "",
	"ipv6_APN_config16": "",
	"ipv6_APN_config17": "",
	"ipv6_APN_config18": "",
	"ipv6_APN_config19": "",
	"m_profile_name": "ProfileSami",
	"profile_name": "",
	"wan_dial": "*99#",
	"apn_select": "manual",
	"pdp_type": "IP",
	"pdp_select": "auto",
	"pdp_addr": "",
	"index": "",
	"Current_index": "1",
	"apn_auto_config": "AT($)($)0($)*99#($)none($)($)($)IP($)1($)($)auto($)($)($)0($)($)($)($)($)($)auto",
	"ipv6_apn_auto_config": "AT($)($)0($)*99#($)none($)($)($)IP($)1($)($)auto($)($)($)0($)($)($)($)($)($)auto",
	"apn_mode": "manual",
	"wan_apn": "internet",
	"ppp_auth_mode": "none",
	"ppp_username": "",
	"ppp_passwd": "",
	"dns_mode": "auto",
	"prefer_dns_manual": "",
	"standby_dns_manual": "",
	"ipv6_wan_apn": "",
	"ipv6_pdp_type": "IP",
	"ipv6_ppp_auth_mode": "",
	"ipv6_ppp_username": "",
	"ipv6_ppp_passwd": "",
	"ipv6_dns_mode": "",
	"ipv6_prefer_dns_manual": "",
	"ipv6_standby_dns_manual": "",
	"apn_num_preset": "",
	"wan_apn_ui": "internet",
	"profile_name_ui": "ProfileSami",
	"pdp_type_ui": "IP",
	"ppp_auth_mode_ui": "none",
	"ppp_username_ui": "",
	"ppp_passwd_ui": "",
	"dns_mode_ui": "auto",
	"prefer_dns_manual_ui": "",
	"standby_dns_manual_ui": "",
	"ipv6_wan_apn_ui": "internet",
	"ipv6_ppp_auth_mode_ui": "none",
	"ipv6_ppp_username_ui": "",
	"ipv6_ppp_passwd_ui": "",
	"ipv6_dns_mode_ui": "",
	"ipv6_prefer_dns_manual_ui": "",
	"ipv6_standby_dns_manual_ui": ""
}